rl_algorithms/Agent.py
rl_algorithms/__init__.py
rl_algorithms/montecarlo/MonteCarlo.py
rl_algorithms/montecarlo/__init__.py
rl_algorithms/policy/ActorCritic.py
rl_algorithms/policy/OptionCritic.py
rl_algorithms/policy/Reinforce.py
rl_algorithms/policy/__init__.py
rl_algorithms/qlearning/DQN.py
rl_algorithms/qlearning/QLearning.py
rl_algorithms/qlearning/__init__.py
rl_algorithms/sarsa/DSN.py
rl_algorithms/sarsa/NStepSarsa.py
rl_algorithms/sarsa/Sarsa.py
rl_algorithms/sarsa/__init__.py
rl_algorithms-0.0.4.dist-info/LICENSE
rl_algorithms-0.0.4.dist-info/METADATA
rl_algorithms-0.0.4.dist-info/WHEEL
rl_algorithms-0.0.4.dist-info/top_level.txt
rl_algorithms-0.0.4.dist-info/RECORD
