Metadata-Version: 2.1
Name: rl-algorithms
Version: 0.0.4
Summary: Implementation of reinforcement learning algorithms
Home-page: https://github.com/blurry-mood/RL-algorithms
Author: Ayoub Assis
Author-email: assis.ayoub@gmail.com
License: LICENSE
Keywords: pytorch reinforcement learning q-learning deep-q-learning
Platform: UNKNOWN
Requires-Python: >=3.7
License-File: LICENSE
Requires-Dist: torch
Requires-Dist: numpy
Requires-Dist: joblib
